goosefs_metastore_client/__init__.py
goosefs_metastore_client/authentication.py
goosefs_metastore_client/goosefs_metastore_client.py
goosefs_metastore_client/builders/__init__.py
goosefs_metastore_client/builders/abstract_builder.py
goosefs_metastore_client/builders/database_builder.py
goosefs_metastore_client/builders/field_schema_builder.py
goosefs_metastore_client/builders/table_builder.py
goosefs_metastore_client-0.1.1.dist-info/licenses/LICENSE
grpc_files/__init__.py
grpc_files/common_pb2.py
grpc_files/common_pb2_grpc.py
grpc_files/job_master_pb2.py
grpc_files/job_master_pb2_grpc.py
grpc_files/sasl_server_pb2.py
grpc_files/sasl_server_pb2_grpc.py
grpc_files/table_master_pb2.py
grpc_files/table_master_pb2_grpc.py
goosefs_metastore_client-0.1.1.dist-info/METADATA
goosefs_metastore_client-0.1.1.dist-info/WHEEL
goosefs_metastore_client-0.1.1.dist-info/top_level.txt
goosefs_metastore_client-0.1.1.dist-info/RECORD
