Metadata-Version: 2.4
Name: goosefs_metastore_client
Version: 0.1.1
Summary: A Python client for connecting to GooseFS Table Master via gRPC
Home-page: https://git.woa.com/tencent-cloud-datalake/goosefs-metastore-client
Author: forwardxu
Author-email: forwardxu@apache.com
License: Apache License 2.0
Keywords: goosefs metastore grpc table-master database
Classifier: Development Status :: 3 - Alpha
Classifier: Intended Audience :: Developers
Classifier: License :: OSI Approved :: Apache Software License
Classifier: Programming Language :: Python :: 3
Classifier: Programming Language :: Python :: 3.7
Classifier: Programming Language :: Python :: 3.8
Classifier: Programming Language :: Python :: 3.9
Classifier: Programming Language :: Python :: 3.10
Classifier: Programming Language :: Python :: 3.11
Requires-Python: >=3.7, <4
License-File: LICENSE
Requires-Dist: grpcio>=1.50.0
Requires-Dist: grpcio-tools>=1.50.0
Requires-Dist: protobuf>=3.20.0
Dynamic: author
Dynamic: description
Dynamic: description-content-type
Dynamic: home-page
Dynamic: keywords
Dynamic: license
Dynamic: license-file
Dynamic: requires-dist
Dynamic: requires-python
Dynamic: summary
